nelson_siegel_svensson/__init__.py
nelson_siegel_svensson/calibrate.py
nelson_siegel_svensson/cli.py
nelson_siegel_svensson/ns.py
nelson_siegel_svensson/nss.py
nelson_siegel_svensson-0.5.0.dist-info/AUTHORS.rst
nelson_siegel_svensson-0.5.0.dist-info/LICENSE
nelson_siegel_svensson-0.5.0.dist-info/METADATA
nelson_siegel_svensson-0.5.0.dist-info/WHEEL
nelson_siegel_svensson-0.5.0.dist-info/entry_points.txt
nelson_siegel_svensson-0.5.0.dist-info/top_level.txt
nelson_siegel_svensson-0.5.0.dist-info/RECORD
