Metadata-Version: 2.1
Name: nelson_siegel_svensson
Version: 0.5.0
Summary: Implementation of the Nelson-Siegel-Svensson interest rate curve model.
Home-page: https://github.com/luphord/nelson_siegel_svensson
Author: luphord
Author-email: luphord@protonmail.com
License: MIT license
Keywords: nelson_siegel_svensson
Classifier: Development Status :: 4 - Beta
Classifier: Intended Audience :: Developers
Classifier: License :: OSI Approved :: MIT License
Classifier: Natural Language :: English
Classifier: Programming Language :: Python :: 3.8
Classifier: Programming Language :: Python :: 3.9
Classifier: Programming Language :: Python :: 3.10
License-File: LICENSE
License-File: AUTHORS.rst
